infi_email/__init__.py
infi_email/config/__init__.py
infi_email/config/config.py
infi_email/service/__init__.py
infi_email/service/email.py
infi_email-0.0.2.dist-info/METADATA
infi_email-0.0.2.dist-info/WHEEL
infi_email-0.0.2.dist-info/top_level.txt
infi_email-0.0.2.dist-info/RECORD
