Metadata-Version: 2.1
Name: infi-email
Version: 0.0.2
Summary: Email package for infinity team
Author: Infinity Team
License: MIT
